odoo/addons/delivery_package_fee/README.rst
odoo/addons/delivery_package_fee/__init__.py
odoo/addons/delivery_package_fee/__manifest__.py
odoo/addons/delivery_package_fee/i18n/delivery_package_fee.pot
odoo/addons/delivery_package_fee/i18n/es.po
odoo/addons/delivery_package_fee/i18n/fr.po
odoo/addons/delivery_package_fee/i18n/it.po
odoo/addons/delivery_package_fee/models/__init__.py
odoo/addons/delivery_package_fee/models/delivery_carrier.py
odoo/addons/delivery_package_fee/models/delivery_package_fee.py
odoo/addons/delivery_package_fee/models/sale_order.py
odoo/addons/delivery_package_fee/models/sale_order_line.py
odoo/addons/delivery_package_fee/models/stock_picking.py
odoo/addons/delivery_package_fee/readme/CONFIGURE.md
odoo/addons/delivery_package_fee/readme/CONTRIBUTORS.md
odoo/addons/delivery_package_fee/readme/CREDITS.md
odoo/addons/delivery_package_fee/readme/DESCRIPTION.md
odoo/addons/delivery_package_fee/security/ir.model.access.csv
odoo/addons/delivery_package_fee/static/description/icon.png
odoo/addons/delivery_package_fee/static/description/index.html
odoo/addons/delivery_package_fee/tests/__init__.py
odoo/addons/delivery_package_fee/tests/test_package_fee.py
odoo/addons/delivery_package_fee/views/delivery_carrier_views.xml
odoo_addon_delivery_package_fee-18.0.1.0.0.3.dist-info/METADATA
odoo_addon_delivery_package_fee-18.0.1.0.0.3.dist-info/WHEEL
odoo_addon_delivery_package_fee-18.0.1.0.0.3.dist-info/top_level.txt
odoo_addon_delivery_package_fee-18.0.1.0.0.3.dist-info/RECORD
